[
 {
  "app": "erpnext",
  "creation": "2026-02-08 11:39:52.630148",
  "docstatus": 0,
  "doctype": "Desktop Icon",
  "hidden": 0,
  "icon": "dashboard",
  "icon_type": "Link",
  "idx": 1,
  "label": "Design Hub",
  "link_to": "Design Hub",
  "link_type": "Workspace",
  "modified": "2026-02-08 11:39:52.630151",
  "modified_by": "Administrator",
  "name": "design-design-hub",
  "owner": "Administrator",
  "parent_icon": "Design",
  "restrict_removal": 0,
  "roles": [],
  "standard": 1,
  "module": "Enhancements Core"
 },
 {
  "app": "erpnext",
  "creation": "2026-02-08 11:39:52.616065",
  "docstatus": 0,
  "doctype": "Desktop Icon",
  "hidden": 0,
  "icon": "dashboard",
  "icon_type": "Link",
  "idx": 1,
  "label": "Executive Hub",
  "link_to": "Executive Hub",
  "link_type": "Workspace",
  "modified": "2026-02-08 11:39:52.616068",
  "modified_by": "Administrator",
  "name": "executive-executive-hub",
  "owner": "Administrator",
  "parent_icon": "Executive",
  "restrict_removal": 0,
  "roles": [],
  "standard": 1,
  "module": "Enhancements Core"
 },
 {
  "app": "erpnext",
  "creation": "2026-02-08 11:39:52.615750",
  "docstatus": 0,
  "doctype": "Desktop Icon",
  "hidden": 0,
  "icon": "briefcase",
  "icon_type": "Folder",
  "idx": 1,
  "label": "Executive",
  "link_to": "Executive",
  "link_type": "Workspace Sidebar",
  "modified": "2026-02-08 11:39:52.615768",
  "modified_by": "Administrator",
  "name": "Executive",
  "owner": "Administrator",
  "parent_icon": "",
  "restrict_removal": 0,
  "roles": [],
  "standard": 1,
  "module": "Enhancements Core"
 },
 {
  "app": "erpnext",
  "creation": "2026-02-08 11:39:52.620429",
  "docstatus": 0,
  "doctype": "Desktop Icon",
  "hidden": 0,
  "icon": "dashboard",
  "icon_type": "Link",
  "idx": 1,
  "label": "Finance Hub",
  "link_to": "Finance Hub",
  "link_type": "Workspace",
  "modified": "2026-02-08 11:39:52.620432",
  "modified_by": "Administrator",
  "name": "finance-finance-hub",
  "owner": "Administrator",
  "parent_icon": "Finance",
  "restrict_removal": 0,
  "roles": [],
  "standard": 1,
  "module": "Enhancements Core"
 },
 {
  "app": "erpnext",
  "creation": "2026-02-08 11:39:52.627355",
  "docstatus": 0,
  "doctype": "Desktop Icon",
  "hidden": 0,
  "icon": "dashboard",
  "icon_type": "Link",
  "idx": 1,
  "label": "Marketing Hub",
  "link_to": "Marketing Hub",
  "link_type": "Workspace",
  "modified": "2026-02-08 11:39:52.627358",
  "modified_by": "Administrator",
  "name": "marketing-marketing-hub",
  "owner": "Administrator",
  "parent_icon": "Marketing",
  "restrict_removal": 0,
  "roles": [],
  "standard": 1,
  "module": "Enhancements Core"
 },
 {
  "app": "erpnext",
  "creation": "2026-02-08 11:39:52.623067",
  "docstatus": 0,
  "doctype": "Desktop Icon",
  "hidden": 0,
  "icon": "dashboard",
  "icon_type": "Link",
  "idx": 1,
  "label": "Operations Hub",
  "link_to": "Operations Hub",
  "link_type": "Workspace",
  "modified": "2026-02-08 11:39:52.623069",
  "modified_by": "Administrator",
  "name": "operations-operations-hub",
  "owner": "Administrator",
  "parent_icon": "Operations",
  "restrict_removal": 0,
  "roles": [],
  "standard": 1,
  "module": "Enhancements Core"
 },
 {
  "app": "erpnext",
  "creation": "2026-02-08 11:39:52.628493",
  "docstatus": 0,
  "doctype": "Desktop Icon",
  "hidden": 0,
  "icon": "dashboard",
  "icon_type": "Link",
  "idx": 1,
  "label": "Production Hub",
  "link_to": "Production Hub",
  "link_type": "Workspace",
  "modified": "2026-02-08 11:39:52.628496",
  "modified_by": "Administrator",
  "name": "production-production-hub",
  "owner": "Administrator",
  "parent_icon": "Production",
  "restrict_removal": 0,
  "roles": [],
  "standard": 1,
  "module": "Enhancements Core"
 },
 {
  "app": "erpnext",
  "creation": "2026-02-08 11:39:52.625640",
  "docstatus": 0,
  "doctype": "Desktop Icon",
  "hidden": 0,
  "icon": "dashboard",
  "icon_type": "Link",
  "idx": 1,
  "label": "Sales Hub",
  "link_to": "Sales Hub",
  "link_type": "Workspace",
  "modified": "2026-02-08 11:39:52.625643",
  "modified_by": "Administrator",
  "name": "sales-sales-hub",
  "owner": "Administrator",
  "parent_icon": "Sales",
  "restrict_removal": 0,
  "roles": [],
  "standard": 1,
  "module": "Enhancements Core"
 },
 {
  "app": "erpnext",
  "creation": "2026-02-08 11:39:52.630357",
  "docstatus": 0,
  "doctype": "Desktop Icon",
  "hidden": 0,
  "icon": "project",
  "icon_type": "Link",
  "idx": 2,
  "label": "Projects",
  "link_to": "Projects",
  "link_type": "Workspace",
  "modified": "2026-02-08 11:39:52.630359",
  "modified_by": "Administrator",
  "name": "design-projects",
  "owner": "Administrator",
  "parent_icon": "Design",
  "restrict_removal": 0,
  "roles": [],
  "standard": 1,
  "module": "Enhancements Core"
 },
 {
  "app": "erpnext",
  "creation": "2026-02-08 11:39:52.616322",
  "docstatus": 0,
  "doctype": "Desktop Icon",
  "hidden": 0,
  "icon": "chart",
  "icon_type": "Link",
  "idx": 2,
  "label": "Reports",
  "link_to": "Reports",
  "link_type": "Workspace",
  "modified": "2026-02-08 11:39:52.616325",
  "modified_by": "Administrator",
  "name": "executive-reports",
  "owner": "Administrator",
  "parent_icon": "Executive",
  "restrict_removal": 0,
  "roles": [],
  "standard": 1,
  "module": "Enhancements Core"
 },
 {
  "app": "erpnext",
  "creation": "2026-02-08 11:39:52.620670",
  "docstatus": 0,
  "doctype": "Desktop Icon",
  "hidden": 0,
  "icon": "shopping-cart",
  "icon_type": "Link",
  "idx": 2,
  "label": "Buying",
  "link_to": "Buying",
  "link_type": "Workspace",
  "modified": "2026-02-08 11:39:52.620673",
  "modified_by": "Administrator",
  "name": "finance-buying",
  "owner": "Administrator",
  "parent_icon": "Finance",
  "restrict_removal": 0,
  "roles": [],
  "standard": 1,
  "module": "Enhancements Core"
 },
 {
  "app": "erpnext",
  "creation": "2026-02-08 11:39:52.620136",
  "docstatus": 0,
  "doctype": "Desktop Icon",
  "hidden": 0,
  "icon": "bank",
  "icon_type": "Folder",
  "idx": 2,
  "label": "Finance",
  "link_to": "Finance",
  "link_type": "Workspace Sidebar",
  "modified": "2026-02-08 11:39:52.620142",
  "modified_by": "Administrator",
  "name": "Finance",
  "owner": "Administrator",
  "parent_icon": "",
  "restrict_removal": 0,
  "roles": [],
  "standard": 1,
  "module": "Enhancements Core"
 },
 {
  "app": "erpnext",
  "creation": "2026-02-08 11:39:52.627549",
  "docstatus": 0,
  "doctype": "Desktop Icon",
  "hidden": 0,
  "icon": "bag",
  "icon_type": "Link",
  "idx": 2,
  "label": "Selling",
  "link_to": "Selling",
  "link_type": "Workspace",
  "modified": "2026-02-08 11:39:52.627551",
  "modified_by": "Administrator",
  "name": "marketing-selling",
  "owner": "Administrator",
  "parent_icon": "Marketing",
  "restrict_removal": 0,
  "roles": [],
  "standard": 1,
  "module": "Enhancements Core"
 },
 {
  "app": "erpnext",
  "creation": "2026-02-08 11:39:52.623318",
  "docstatus": 0,
  "doctype": "Desktop Icon",
  "hidden": 0,
  "icon": "life-buoy",
  "icon_type": "Link",
  "idx": 2,
  "label": "Helpdesk",
  "link_to": "Helpdesk",
  "link_type": "Workspace",
  "modified": "2026-02-08 11:39:52.623320",
  "modified_by": "Administrator",
  "name": "operations-helpdesk",
  "owner": "Administrator",
  "parent_icon": "Operations",
  "restrict_removal": 0,
  "roles": [],
  "standard": 1,
  "module": "Enhancements Core"
 },
 {
  "app": "erpnext",
  "creation": "2026-02-08 11:39:52.628699",
  "docstatus": 0,
  "doctype": "Desktop Icon",
  "hidden": 0,
  "icon": "project",
  "icon_type": "Link",
  "idx": 2,
  "label": "Projects",
  "link_to": "Projects",
  "link_type": "Workspace",
  "modified": "2026-02-08 11:39:52.628701",
  "modified_by": "Administrator",
  "name": "production-projects",
  "owner": "Administrator",
  "parent_icon": "Production",
  "restrict_removal": 0,
  "roles": [],
  "standard": 1,
  "module": "Enhancements Core"
 },
 {
  "app": "erpnext",
  "creation": "2026-02-08 11:39:52.625851",
  "docstatus": 0,
  "doctype": "Desktop Icon",
  "hidden": 0,
  "icon": "users",
  "icon_type": "Link",
  "idx": 2,
  "label": "CRM",
  "link_to": "CRM",
  "link_type": "Workspace",
  "modified": "2026-02-08 11:39:52.625856",
  "modified_by": "Administrator",
  "name": "sales-crm",
  "owner": "Administrator",
  "parent_icon": "Sales",
  "restrict_removal": 0,
  "roles": [],
  "standard": 1,
  "module": "Enhancements Core"
 },
 {
  "app": "erpnext",
  "creation": "2026-02-08 11:39:52.630651",
  "docstatus": 0,
  "doctype": "Desktop Icon",
  "hidden": 0,
  "icon": "shopping-cart",
  "icon_type": "Link",
  "idx": 3,
  "label": "Buying",
  "link_to": "Buying",
  "link_type": "Workspace",
  "modified": "2026-02-08 11:39:52.630656",
  "modified_by": "Administrator",
  "name": "design-buying",
  "owner": "Administrator",
  "parent_icon": "Design",
  "restrict_removal": 0,
  "roles": [],
  "standard": 1,
  "module": "Enhancements Core"
 },
 {
  "app": "erpnext",
  "creation": "2026-02-08 11:39:52.620874",
  "docstatus": 0,
  "doctype": "Desktop Icon",
  "hidden": 0,
  "icon": "bag",
  "icon_type": "Link",
  "idx": 3,
  "label": "Selling",
  "link_to": "Selling",
  "link_type": "Workspace",
  "modified": "2026-02-08 11:39:52.620877",
  "modified_by": "Administrator",
  "name": "finance-selling",
  "owner": "Administrator",
  "parent_icon": "Finance",
  "restrict_removal": 0,
  "roles": [],
  "standard": 1,
  "module": "Enhancements Core"
 },
 {
  "app": "erpnext",
  "creation": "2026-02-08 11:39:52.627738",
  "docstatus": 0,
  "doctype": "Desktop Icon",
  "hidden": 0,
  "icon": "users",
  "icon_type": "Link",
  "idx": 3,
  "label": "CRM",
  "link_to": "CRM",
  "link_type": "Workspace",
  "modified": "2026-02-08 11:39:52.627740",
  "modified_by": "Administrator",
  "name": "marketing-crm",
  "owner": "Administrator",
  "parent_icon": "Marketing",
  "restrict_removal": 0,
  "roles": [],
  "standard": 1,
  "module": "Enhancements Core"
 },
 {
  "app": "erpnext",
  "creation": "2026-02-08 11:39:52.623583",
  "docstatus": 0,
  "doctype": "Desktop Icon",
  "hidden": 0,
  "icon": "book",
  "icon_type": "Link",
  "idx": 3,
  "label": "LMS",
  "link_to": "LMS",
  "link_type": "Workspace",
  "modified": "2026-02-08 11:39:52.623588",
  "modified_by": "Administrator",
  "name": "operations-lms",
  "owner": "Administrator",
  "parent_icon": "Operations",
  "restrict_removal": 0,
  "roles": [],
  "standard": 1,
  "module": "Enhancements Core"
 },
 {
  "app": "erpnext",
  "creation": "2026-02-08 11:39:52.622853",
  "docstatus": 0,
  "doctype": "Desktop Icon",
  "hidden": 0,
  "icon": "cogs",
  "icon_type": "Folder",
  "idx": 3,
  "label": "Operations",
  "link_to": "Operations",
  "link_type": "Workspace Sidebar",
  "modified": "2026-02-08 11:39:52.622857",
  "modified_by": "Administrator",
  "name": "Operations",
  "owner": "Administrator",
  "parent_icon": "",
  "restrict_removal": 0,
  "roles": [],
  "standard": 1,
  "module": "Enhancements Core"
 },
 {
  "app": "erpnext",
  "creation": "2026-02-08 11:39:52.629030",
  "docstatus": 0,
  "doctype": "Desktop Icon",
  "hidden": 0,
  "icon": "users",
  "icon_type": "Link",
  "idx": 3,
  "label": "CRM",
  "link_to": "CRM",
  "link_type": "Workspace",
  "modified": "2026-02-08 11:39:52.629035",
  "modified_by": "Administrator",
  "name": "production-crm",
  "owner": "Administrator",
  "parent_icon": "Production",
  "restrict_removal": 0,
  "roles": [],
  "standard": 1,
  "module": "Enhancements Core"
 },
 {
  "app": "erpnext",
  "creation": "2026-02-08 11:39:52.626168",
  "docstatus": 0,
  "doctype": "Desktop Icon",
  "hidden": 0,
  "icon": "bag",
  "icon_type": "Link",
  "idx": 3,
  "label": "Selling",
  "link_to": "Selling",
  "link_type": "Workspace",
  "modified": "2026-02-08 11:39:52.626172",
  "modified_by": "Administrator",
  "name": "sales-selling",
  "owner": "Administrator",
  "parent_icon": "Sales",
  "restrict_removal": 0,
  "roles": [],
  "standard": 1,
  "module": "Enhancements Core"
 },
 {
  "app": "erpnext",
  "creation": "2026-02-08 11:39:52.630898",
  "docstatus": 0,
  "doctype": "Desktop Icon",
  "hidden": 0,
  "icon": "bag",
  "icon_type": "Link",
  "idx": 4,
  "label": "Selling",
  "link_to": "Selling",
  "link_type": "Workspace",
  "modified": "2026-02-08 11:39:52.630901",
  "modified_by": "Administrator",
  "name": "design-selling",
  "owner": "Administrator",
  "parent_icon": "Design",
  "restrict_removal": 0,
  "roles": [],
  "standard": 1,
  "module": "Enhancements Core"
 },
 {
  "app": "erpnext",
  "creation": "2026-02-08 11:39:52.621161",
  "docstatus": 0,
  "doctype": "Desktop Icon",
  "hidden": 0,
  "icon": "archive",
  "icon_type": "Link",
  "idx": 4,
  "label": "Assets",
  "link_to": "Assets",
  "link_type": "Workspace",
  "modified": "2026-02-08 11:39:52.621164",
  "modified_by": "Administrator",
  "name": "finance-assets",
  "owner": "Administrator",
  "parent_icon": "Finance",
  "restrict_removal": 0,
  "roles": [],
  "standard": 1,
  "module": "Enhancements Core"
 },
 {
  "app": "erpnext",
  "creation": "2026-02-08 11:39:52.623844",
  "docstatus": 0,
  "doctype": "Desktop Icon",
  "hidden": 0,
  "icon": "users",
  "icon_type": "Link",
  "idx": 4,
  "label": "CRM",
  "link_to": "CRM",
  "link_type": "Workspace",
  "modified": "2026-02-08 11:39:52.623847",
  "modified_by": "Administrator",
  "name": "operations-crm",
  "owner": "Administrator",
  "parent_icon": "Operations",
  "restrict_removal": 0,
  "roles": [],
  "standard": 1,
  "module": "Enhancements Core"
 },
 {
  "app": "erpnext",
  "creation": "2026-02-08 11:39:52.629318",
  "docstatus": 0,
  "doctype": "Desktop Icon",
  "hidden": 0,
  "icon": "calendar",
  "icon_type": "Link",
  "idx": 4,
  "label": "ToDo Calendar",
  "link_to": "/desk/todo/view/calendar/default",
  "link_type": "Url",
  "modified": "2026-02-08 11:39:52.629321",
  "modified_by": "Administrator",
  "name": "production-todo-calendar",
  "owner": "Administrator",
  "parent_icon": "Production",
  "restrict_removal": 0,
  "roles": [],
  "standard": 1,
  "module": "Enhancements Core"
 },
 {
  "app": "erpnext",
  "creation": "2026-02-08 11:39:52.626385",
  "docstatus": 0,
  "doctype": "Desktop Icon",
  "hidden": 0,
  "icon": "shopping-cart",
  "icon_type": "Link",
  "idx": 4,
  "label": "Buying",
  "link_to": "Buying",
  "link_type": "Workspace",
  "modified": "2026-02-08 11:39:52.626388",
  "modified_by": "Administrator",
  "name": "sales-buying",
  "owner": "Administrator",
  "parent_icon": "Sales",
  "restrict_removal": 0,
  "roles": [],
  "standard": 1,
  "module": "Enhancements Core"
 },
 {
  "app": "erpnext",
  "creation": "2026-02-08 11:39:52.625410",
  "docstatus": 0,
  "doctype": "Desktop Icon",
  "hidden": 0,
  "icon": "bill",
  "icon_type": "Folder",
  "idx": 4,
  "label": "Sales",
  "link_to": "Sales",
  "link_type": "Workspace Sidebar",
  "modified": "2026-02-08 11:39:52.625413",
  "modified_by": "Administrator",
  "name": "Sales",
  "owner": "Administrator",
  "parent_icon": "",
  "restrict_removal": 0,
  "roles": [],
  "standard": 1,
  "module": "Enhancements Core"
 },
 {
  "app": "erpnext",
  "creation": "2026-02-08 11:39:52.631120",
  "docstatus": 0,
  "doctype": "Desktop Icon",
  "hidden": 0,
  "icon": "users",
  "icon_type": "Link",
  "idx": 5,
  "label": "CRM",
  "link_to": "CRM",
  "link_type": "Workspace",
  "modified": "2026-02-08 11:39:52.631122",
  "modified_by": "Administrator",
  "name": "design-crm",
  "owner": "Administrator",
  "parent_icon": "Design",
  "restrict_removal": 0,
  "roles": [],
  "standard": 1,
  "module": "Enhancements Core"
 },
 {
  "app": "erpnext",
  "creation": "2026-02-08 11:39:52.621479",
  "docstatus": 0,
  "doctype": "Desktop Icon",
  "hidden": 0,
  "icon": "project",
  "icon_type": "Link",
  "idx": 5,
  "label": "Projects",
  "link_to": "Projects",
  "link_type": "Workspace",
  "modified": "2026-02-08 11:39:52.621484",
  "modified_by": "Administrator",
  "name": "finance-projects",
  "owner": "Administrator",
  "parent_icon": "Finance",
  "restrict_removal": 0,
  "roles": [],
  "standard": 1,
  "module": "Enhancements Core"
 },
 {
  "app": "erpnext",
  "creation": "2026-02-08 11:39:52.627157",
  "docstatus": 0,
  "doctype": "Desktop Icon",
  "hidden": 0,
  "icon": "broadcast",
  "icon_type": "Folder",
  "idx": 5,
  "label": "Marketing",
  "link_to": "Marketing",
  "link_type": "Workspace Sidebar",
  "modified": "2026-02-08 11:39:52.627160",
  "modified_by": "Administrator",
  "name": "Marketing",
  "owner": "Administrator",
  "parent_icon": "",
  "restrict_removal": 0,
  "roles": [],
  "standard": 1,
  "module": "Enhancements Core"
 },
 {
  "app": "erpnext",
  "creation": "2026-02-08 11:39:52.624058",
  "docstatus": 0,
  "doctype": "Desktop Icon",
  "hidden": 0,
  "icon": "project",
  "icon_type": "Link",
  "idx": 5,
  "label": "Projects",
  "link_to": "Projects",
  "link_type": "Workspace",
  "modified": "2026-02-08 11:39:52.624061",
  "modified_by": "Administrator",
  "name": "operations-projects",
  "owner": "Administrator",
  "parent_icon": "Operations",
  "restrict_removal": 0,
  "roles": [],
  "standard": 1,
  "module": "Enhancements Core"
 },
 {
  "app": "erpnext",
  "creation": "2026-02-08 11:39:52.626653",
  "docstatus": 0,
  "doctype": "Desktop Icon",
  "hidden": 0,
  "icon": "box",
  "icon_type": "Link",
  "idx": 5,
  "label": "Stock",
  "link_to": "Stock",
  "link_type": "Workspace",
  "modified": "2026-02-08 11:39:52.626657",
  "modified_by": "Administrator",
  "name": "sales-stock",
  "owner": "Administrator",
  "parent_icon": "Sales",
  "restrict_removal": 0,
  "roles": [],
  "standard": 1,
  "module": "Enhancements Core"
 },
 {
  "app": "erpnext",
  "creation": "2026-02-08 11:39:52.621820",
  "docstatus": 0,
  "doctype": "Desktop Icon",
  "hidden": 0,
  "icon": "box",
  "icon_type": "Link",
  "idx": 6,
  "label": "Stock",
  "link_to": "Stock",
  "link_type": "Workspace",
  "modified": "2026-02-08 11:39:52.621824",
  "modified_by": "Administrator",
  "name": "finance-stock",
  "owner": "Administrator",
  "parent_icon": "Finance",
  "restrict_removal": 0,
  "roles": [],
  "standard": 1,
  "module": "Enhancements Core"
 },
 {
  "app": "erpnext",
  "creation": "2026-02-08 11:39:52.624260",
  "docstatus": 0,
  "doctype": "Desktop Icon",
  "hidden": 0,
  "icon": "box",
  "icon_type": "Link",
  "idx": 6,
  "label": "Stock",
  "link_to": "Stock",
  "link_type": "Workspace",
  "modified": "2026-02-08 11:39:52.624263",
  "modified_by": "Administrator",
  "name": "operations-stock",
  "owner": "Administrator",
  "parent_icon": "Operations",
  "restrict_removal": 0,
  "roles": [],
  "standard": 1,
  "module": "Enhancements Core"
 },
 {
  "app": "erpnext",
  "creation": "2026-02-08 11:39:52.628274",
  "docstatus": 0,
  "doctype": "Desktop Icon",
  "hidden": 0,
  "icon": "factory",
  "icon_type": "Folder",
  "idx": 6,
  "label": "Production",
  "link_to": "Production",
  "link_type": "Workspace Sidebar",
  "modified": "2026-02-08 11:39:52.628277",
  "modified_by": "Administrator",
  "name": "Production",
  "owner": "Administrator",
  "parent_icon": "",
  "restrict_removal": 0,
  "roles": [],
  "standard": 1,
  "module": "Enhancements Core"
 },
 {
  "app": "erpnext",
  "creation": "2026-02-08 11:39:52.629913",
  "docstatus": 0,
  "doctype": "Desktop Icon",
  "hidden": 0,
  "icon": "edit",
  "icon_type": "Folder",
  "idx": 7,
  "label": "Design",
  "link_to": "Design",
  "link_type": "Workspace Sidebar",
  "modified": "2026-02-08 11:39:52.629916",
  "modified_by": "Administrator",
  "name": "Design",
  "owner": "Administrator",
  "parent_icon": "",
  "restrict_removal": 0,
  "roles": [],
  "standard": 1,
  "module": "Enhancements Core"
 },
 {
  "app": "erpnext",
  "creation": "2026-02-08 11:39:52.622101",
  "docstatus": 0,
  "doctype": "Desktop Icon",
  "hidden": 0,
  "icon": "file-text",
  "icon_type": "Link",
  "idx": 7,
  "label": "Invoicing",
  "link_to": "Accounting",
  "link_type": "Workspace",
  "modified": "2026-02-08 11:39:52.622104",
  "modified_by": "Administrator",
  "name": "finance-invoicing",
  "owner": "Administrator",
  "parent_icon": "Finance",
  "restrict_removal": 0,
  "roles": [],
  "standard": 1,
  "module": "Enhancements Core"
 },
 {
  "app": "erpnext",
  "creation": "2026-02-08 11:39:52.624547",
  "docstatus": 0,
  "doctype": "Desktop Icon",
  "hidden": 0,
  "icon": "shopping-cart",
  "icon_type": "Link",
  "idx": 7,
  "label": "Buying",
  "link_to": "Buying",
  "link_type": "Workspace",
  "modified": "2026-02-08 11:39:52.624551",
  "modified_by": "Administrator",
  "name": "operations-buying",
  "owner": "Administrator",
  "parent_icon": "Operations",
  "restrict_removal": 0,
  "roles": [],
  "standard": 1,
  "module": "Enhancements Core"
 },
 {
  "app": "erpnext",
  "creation": "2026-02-08 11:39:52.622340",
  "docstatus": 0,
  "doctype": "Desktop Icon",
  "hidden": 0,
  "icon": "users",
  "icon_type": "Link",
  "idx": 8,
  "label": "CRM",
  "link_to": "CRM",
  "link_type": "Workspace",
  "modified": "2026-02-08 11:39:52.622342",
  "modified_by": "Administrator",
  "name": "finance-crm",
  "owner": "Administrator",
  "parent_icon": "Finance",
  "restrict_removal": 0,
  "roles": [],
  "standard": 1,
  "module": "Enhancements Core"
 },
 {
  "app": "erpnext",
  "creation": "2026-02-08 11:39:52.624877",
  "docstatus": 0,
  "doctype": "Desktop Icon",
  "hidden": 0,
  "icon": "bag",
  "icon_type": "Link",
  "idx": 8,
  "label": "Selling",
  "link_to": "Selling",
  "link_type": "Workspace",
  "modified": "2026-02-08 11:39:52.624880",
  "modified_by": "Administrator",
  "name": "operations-selling",
  "owner": "Administrator",
  "parent_icon": "Operations",
  "restrict_removal": 0,
  "roles": [],
  "standard": 1,
  "module": "Enhancements Core"
 }
]